README.txt
setup.py
docs/HISTORY.txt
docs/INSTALL.txt
docs/LICENSE.GPL
docs/LICENSE.txt
inquant/__init__.py
inquant.portlet.contextualrecentitems.egg-info/PKG-INFO
inquant.portlet.contextualrecentitems.egg-info/SOURCES.txt
inquant.portlet.contextualrecentitems.egg-info/dependency_links.txt
inquant.portlet.contextualrecentitems.egg-info/entry_points.txt
inquant.portlet.contextualrecentitems.egg-info/namespace_packages.txt
inquant.portlet.contextualrecentitems.egg-info/not-zip-safe
inquant.portlet.contextualrecentitems.egg-info/requires.txt
inquant.portlet.contextualrecentitems.egg-info/top_level.txt
inquant/portlet/__init__.py
inquant/portlet/contextualrecentitems/CHANGELOG
inquant/portlet/contextualrecentitems/README.rst
inquant/portlet/contextualrecentitems/__init__.py
inquant/portlet/contextualrecentitems/configure.zcml
inquant/portlet/contextualrecentitems/contextual_recent_modified.pt
inquant/portlet/contextualrecentitems/contextualrecentitems.pt
inquant/portlet/contextualrecentitems/contextualrecentitems.py
inquant/portlet/contextualrecentitems/interfaces.py
inquant/portlet/contextualrecentitems/version.txt
inquant/portlet/contextualrecentitems/profiles/default/portlets.xml
inquant/portlet/contextualrecentitems/tests/__init__.py
inquant/portlet/contextualrecentitems/tests/base.py
inquant/portlet/contextualrecentitems/tests/test_portlet.py
