Metadata-Version: 1.0
Name: inquant.portlet.contextualrecentitems
Version: 0.2.1
Summary: A Plone Portlet which displays custom recent types
Home-page: http://www.inquant.de
Author: Ramon Bartl
Author-email: ramon.bartl@inquant.de
License: GPL
Platform: UNKNOWN
Classifier: Framework :: Plone
Classifier: Framework :: Zope2
Classifier: Framework :: Zope3
Classifier: Programming Language :: Python
Classifier: Topic :: Software Development :: Libraries :: Python Modules
